MANIFEST.in
README.md
README.txt
setup.cfg
setup.py
seo_meta_fields/__init__.py
seo_meta_fields/__init__.pyc
seo_meta_fields/admin.py
seo_meta_fields/admin.pyc
seo_meta_fields/apps.py
seo_meta_fields/models.py
seo_meta_fields/models.pyc
seo_meta_fields/tests.py
seo_meta_fields/views.py
seo_meta_fields.egg-info/PKG-INFO
seo_meta_fields.egg-info/SOURCES.txt
seo_meta_fields.egg-info/dependency_links.txt
seo_meta_fields.egg-info/not-zip-safe
seo_meta_fields.egg-info/top_level.txt
seo_meta_fields/migrations/0001_initial.py
seo_meta_fields/migrations/0001_initial.pyc
seo_meta_fields/migrations/__init__.py
seo_meta_fields/migrations/__init__.pyc