Metadata-Version: 1.1
Name: seo-meta-fields
Version: 1.6
Summary: Meta Management for Django APP
Home-page: https://github.com/hbansal0122/meta_management
Author: Himanshu Bansal
Author-email: hbansal0122@gmail.com
License: UNKNOWN
Download-URL: https://github.com/hbansal0122/meta_management/archive/master.zip
Keywords: meta,seo,sitemap
Platform: UNKNOWN
